tail_recursion/__init__.py
tail_recursion/_impl.py
tail_recursion-1.1.1.dist-info/WHEEL
tail_recursion-1.1.1.dist-info/METADATA
tail_recursion-1.1.1.dist-info/RECORD
