Metadata-Version: 2.1
Name: tail-recursion
Version: 1.1.1
Summary: Tail call recursion in Python
Author: Incomplete
Author-email: incomplete@aixon.co
Requires-Python: >=3.6
Classifier: Programming Language :: Python :: 3
Classifier: Programming Language :: Python :: 3.6
Classifier: Programming Language :: Python :: 3.7
Classifier: Programming Language :: Python :: 3.8
Classifier: Programming Language :: Python :: 3.9
